docs/conf.py
dynakw/__init__.py
dynakw/core/__init__.py
dynakw/core/enums.py
dynakw/core/keyword_file.py
dynakw/keywords/BOUNDARY_PRESCRIBED_MOTION.py
dynakw/keywords/ELEMENT_SHELL.py
dynakw/keywords/ELEMENT_SOLID.py
dynakw/keywords/MAT_ELASTIC.py
dynakw/keywords/NODE.py
dynakw/keywords/PARAMETER.py
dynakw/keywords/PARAMETER_EXPRESSION.py
dynakw/keywords/PART.py
dynakw/keywords/SECTION_SHELL.py
dynakw/keywords/SECTION_SOLID.py
dynakw/keywords/UNKNOWN.py
dynakw/keywords/__init__.py
dynakw/keywords/lsdyna_keyword.py
dynakw/utils/__init__.py
dynakw/utils/extract_pdf_pages.py
dynakw/utils/format_parser.py
dynakw/utils/get_chapter.py
dynakw/utils/logger.py
dynakw-1.1.2.dist-info/licenses/LICENSE.md
examples/convert_to_radioss.py
examples/debug_reader.py
examples/display_mesh.py
examples/edit_keywords.py
examples/parameters.py
examples/print_keyword.py
examples/read_write.py
test/notyet_full_files.py
test/test_keywords.py
test/test_parameters.py
test/utils/file_splitter.py
dynakw-1.1.2.dist-info/METADATA
dynakw-1.1.2.dist-info/WHEEL
dynakw-1.1.2.dist-info/entry_points.txt
dynakw-1.1.2.dist-info/top_level.txt
dynakw-1.1.2.dist-info/RECORD
